pymess/__init__.py
pymess/config.py
pymess/enums.py
pymess/sender.py
pymess/version.py
pymess/backend/__init__.py
pymess/backend/controlers.py
pymess/backend/routers.py
pymess/backend/dialer/__init__.py
pymess/backend/dialer/daktela.py
pymess/backend/dialer/dummy.py
pymess/backend/emails/__init__.py
pymess/backend/emails/dummy.py
pymess/backend/emails/mandrill.py
pymess/backend/emails/smtp.py
pymess/backend/push/__init__.py
pymess/backend/push/dummy.py
pymess/backend/push/onesignal.py
pymess/backend/sms/__init__.py
pymess/backend/sms/ats_sms_operator.py
pymess/backend/sms/dummy.py
pymess/backend/sms/sms_operator.py
pymess/backend/sms/sns.py
pymess/backend/sms/twilio.py
pymess/locale/cs/LC_MESSAGES/django.mo
pymess/locale/cs/LC_MESSAGES/django.po
pymess/management/__init__.py
pymess/management/commands/__init__.py
pymess/management/commands/check_dialer_status.py
pymess/management/commands/check_sms_delivery.py
pymess/management/commands/dump_emails.py
pymess/management/commands/pull_emails_info.py
pymess/management/commands/send_messages_batch.py
pymess/management/commands/sync_emails.py
pymess/migrations/0001_initial.py
pymess/migrations/0002_emailmessage_number_of_send_attempts.py
pymess/migrations/0003_dialer.py
pymess/migrations/0004_dialermessage_is_final_state.py
pymess/migrations/0005_push_notifications.py
pymess/migrations/0006_auto_20190322_1712.py
pymess/migrations/0007_auto_20190401_1145.py
pymess/migrations/0008_auto_20190726_1459.py
pymess/migrations/0009_20191108_2007.py
pymess/migrations/0010_20191120_1002.py
pymess/migrations/0011_auto_20191210_1749.py
pymess/migrations/0012_migration.py
pymess/migrations/0013_migration.py
pymess/migrations/0014_migration.py
pymess/migrations/0015_auto_20200110_0904.py
pymess/migrations/0016_migration.py
pymess/migrations/0017_migration.py
pymess/migrations/0018_migration.py
pymess/migrations/0019_migration.py
pymess/migrations/0020_migration.py
pymess/migrations/0021_migration.py
pymess/migrations/0022_migration.py
skip_django_pymess-0.15.3.dist-info/licenses/LICENSE
skip_django_pymess-0.15.3.dist-info/METADATA
skip_django_pymess-0.15.3.dist-info/WHEEL
skip_django_pymess-0.15.3.dist-info/top_level.txt
skip_django_pymess-0.15.3.dist-info/RECORD
