Metadata-Version: 2.4
Name: skip-django-pymess
Version: 0.15.3
Summary: Pymess is a Django framework for sending messages
Home-page: https://github.com/skip-pay/django-pymess
Author: Lubos Matl,Oskar Hollman
Author-email: matllubos@gmail.com
License: LGPL
Classifier: Development Status :: 3 - Alpha
Classifier: Framework :: Django
Classifier: Intended Audience :: Developers
Classifier: License :: OSI Approved :: BSD License
Classifier: Operating System :: OS Independent
Classifier: Programming Language :: Python
Classifier: Topic :: Internet :: WWW/HTTP
License-File: LICENSE
Requires-Dist: django>=4.2
Requires-Dist: skip-django-chamber>=0.7.2
Requires-Dist: beautifulsoup4>=4.8.0
Requires-Dist: skip-django-choice-enumfields>=1.1.3.2
Requires-Dist: python-dateutil>=2.9.0
Dynamic: author
Dynamic: author-email
Dynamic: classifier
Dynamic: description
Dynamic: description-content-type
Dynamic: home-page
Dynamic: license
Dynamic: license-file
Dynamic: requires-dist
Dynamic: summary
